gimbel/__init__.py
gimbel/__main__.py
gimbel/gimbel_scraper.py
pandasbots_gimbel-1.6.3.dist-info/LICENSE.txt
pandasbots_gimbel-1.6.3.dist-info/METADATA
pandasbots_gimbel-1.6.3.dist-info/WHEEL
pandasbots_gimbel-1.6.3.dist-info/top_level.txt
pandasbots_gimbel-1.6.3.dist-info/RECORD
