Metadata-Version: 2.1
Name: pandasbots-gimbel
Version: 1.6.3
Summary: This package allows you to scrap Gimbel Mexicana website and return product infos.
Home-page: https://pandasbots.com
Author: Rafael Klanfer Nunes
Author-email: comercial@pandasbots.com
Project-URL: Source Code, https://github.com/PandasBots/pandasbots-gimbel
Classifier: Programming Language :: Python :: 3
Classifier: License :: OSI Approved :: MIT License
Classifier: Operating System :: OS Independent
Requires-Python: >=3.6
License-File: LICENSE.txt
Requires-Dist: pandas
Requires-Dist: selenium
Requires-Dist: webdriver-manager
Requires-Dist: beautifulsoup4
Requires-Dist: openpyxl
